pyminc/__init__.py
pyminc/volumes/__init__.py
pyminc/volumes/factory.py
pyminc/volumes/hyperslab.py
pyminc/volumes/libpyminc2.py
pyminc/volumes/volumes.py
pyminc-0.57.data/scripts/pyminc_test2.py
pyminc-0.57.data/scripts/sva2mnc.py
pyminc-0.57.dist-info/LICENSE
pyminc-0.57.dist-info/METADATA
pyminc-0.57.dist-info/WHEEL
pyminc-0.57.dist-info/top_level.txt
pyminc-0.57.dist-info/RECORD
